python_orange_sms/__init__.py
python_orange_sms/utils.py
python_orange_sms-0.1.4.dist-info/METADATA
python_orange_sms-0.1.4.dist-info/WHEEL
python_orange_sms-0.1.4.dist-info/top_level.txt
python_orange_sms-0.1.4.dist-info/RECORD
