Metadata-Version: 2.1
Name: python-orange-sms
Version: 0.1.4
Summary: Sending sms to orange api with python
Home-page: https://github.com/ged-flod/python_orange_sms
Author: Ged Flod
Author-email: gedeon@comptelab.com
License: MIT
Download-URL: https://pypi.org/project/python_orange_sms/
Keywords: orange sms,python orange sms,python-orange-sms,python-orange
Platform: UNKNOWN
Requires-Python: >=3.6
Requires-Dist: requests (==2.25.1)
Requires-Dist: certifi (==2020.12.5)
Requires-Dist: chardet (==4.0.0)
Requires-Dist: idna (==2.10)
Requires-Dist: urllib3 (==1.26.4)
